monaco/__init__.py
monaco/models.py
monaco/widgets.py
monaco/static/monaco.config.js
monaco/static/monaco.custom.css
monaco/static/monaco/loader.js
monaco/static/monaco/vs/base/worker/workerMain.js
monaco/static/monaco/vs/basic-languages/abap/abap.js
monaco/static/monaco/vs/basic-languages/apex/apex.js
monaco/static/monaco/vs/basic-languages/azcli/azcli.js
monaco/static/monaco/vs/basic-languages/bat/bat.js
monaco/static/monaco/vs/basic-languages/clojure/clojure.js
monaco/static/monaco/vs/basic-languages/coffee/coffee.js
monaco/static/monaco/vs/basic-languages/cpp/cpp.js
monaco/static/monaco/vs/basic-languages/csharp/csharp.js
monaco/static/monaco/vs/basic-languages/csp/csp.js
monaco/static/monaco/vs/basic-languages/css/css.js
monaco/static/monaco/vs/basic-languages/dockerfile/dockerfile.js
monaco/static/monaco/vs/basic-languages/fsharp/fsharp.js
monaco/static/monaco/vs/basic-languages/go/go.js
monaco/static/monaco/vs/basic-languages/graphql/graphql.js
monaco/static/monaco/vs/basic-languages/handlebars/handlebars.js
monaco/static/monaco/vs/basic-languages/html/html.js
monaco/static/monaco/vs/basic-languages/ini/ini.js
monaco/static/monaco/vs/basic-languages/java/java.js
monaco/static/monaco/vs/basic-languages/javascript/javascript.js
monaco/static/monaco/vs/basic-languages/kotlin/kotlin.js
monaco/static/monaco/vs/basic-languages/less/less.js
monaco/static/monaco/vs/basic-languages/lua/lua.js
monaco/static/monaco/vs/basic-languages/markdown/markdown.js
monaco/static/monaco/vs/basic-languages/msdax/msdax.js
monaco/static/monaco/vs/basic-languages/mysql/mysql.js
monaco/static/monaco/vs/basic-languages/objective-c/objective-c.js
monaco/static/monaco/vs/basic-languages/pascal/pascal.js
monaco/static/monaco/vs/basic-languages/pascaligo/pascaligo.js
monaco/static/monaco/vs/basic-languages/perl/perl.js
monaco/static/monaco/vs/basic-languages/pgsql/pgsql.js
monaco/static/monaco/vs/basic-languages/php/php.js
monaco/static/monaco/vs/basic-languages/postiats/postiats.js
django_monaco_old-0.1.dist-info/LICENSE
django_monaco_old-0.1.dist-info/METADATA
django_monaco_old-0.1.dist-info/WHEEL
django_monaco_old-0.1.dist-info/top_level.txt
django_monaco_old-0.1.dist-info/RECORD
