Metadata-Version: 2.1
Name: django-monaco-old
Version: 0.1
Summary: Monaco editor widgets in the Django Admin
Home-page: UNKNOWN
Author: Ayush Shanker
License: MIT
Keywords: django<1.11,monaco
Platform: OS Independent
Requires-Dist: Django (<1.11)
